README.rst
setup.py
ConcordanceCrawler/__init__.py
ConcordanceCrawler/__main__.py
ConcordanceCrawler.egg-info/PKG-INFO
ConcordanceCrawler.egg-info/SOURCES.txt
ConcordanceCrawler.egg-info/dependency_links.txt
ConcordanceCrawler.egg-info/entry_points.txt
ConcordanceCrawler.egg-info/requires.txt
ConcordanceCrawler.egg-info/top_level.txt
ConcordanceCrawler/app/__init__.py
ConcordanceCrawler/app/app.py
ConcordanceCrawler/app/load_from_corpus.py
ConcordanceCrawler/app/output_formatter.py
ConcordanceCrawler/core/__init__.py
ConcordanceCrawler/core/bazwords.py
ConcordanceCrawler/core/concordance_crawler.py
ConcordanceCrawler/core/encoding.py
ConcordanceCrawler/core/lemmatizer_concordance_filter.py
ConcordanceCrawler/core/limited_buffer.py
ConcordanceCrawler/core/links.py
ConcordanceCrawler/core/logging_crawler.py
ConcordanceCrawler/core/parsing.py
ConcordanceCrawler/core/segmenter.py
ConcordanceCrawler/core/simple_concordance_filter.py
ConcordanceCrawler/core/urlrequest.py
ConcordanceCrawler/core/user_agents.py
ConcordanceCrawler/core/visible_text.py
ConcordanceCrawler/core/visitor.py
ConcordanceCrawler/core/words_lower.py
ConcordanceCrawler/core/eng_detect/__init__.py
ConcordanceCrawler/core/eng_detect/eng_detect.py
ConcordanceCrawler/core/eng_detect/english_samples.py
ConcordanceCrawler/core/eng_detect/freq.py
ConcordanceCrawler/core/eng_detect/frequencies.py
ConcordanceCrawler/core/eng_detect/manual_tests.py
ConcordanceCrawler/core/eng_detect/ngrams_extractor.py
ConcordanceCrawler/core/eng_detect/nonenglish_samples.py
ConcordanceCrawler/core/eng_detect/plots.py
ConcordanceCrawler/core/eng_detect/prepare_thresholds.py
ConcordanceCrawler/core/eng_detect/thresholds.py
ConcordanceCrawler/tests/__init__.py
ConcordanceCrawler/tests/crawler_tests.py
ConcordanceCrawler/tests/eng_detect_tests.py
ConcordanceCrawler/tests/formatter_tests.py
ConcordanceCrawler/tests/links_tests.py
ConcordanceCrawler/tests/visitor_tests.py