Metadata-Version: 1.1
Name: ConcordanceCrawler
Version: 1.0.2
Summary: A module for automatic concordance extraction from the Internet
Home-page: https://github.com/Gldkslfmsd/concordance-crawler
Author: Dominik Macháček
Author-email: gldkslfmsd@gmail.com
License: MIT
Download-URL: http://pypi.python.org/pypi/ConcordanceCrawler
Keywords: concordance,crawling,corpus,Internet
Platform: any
Classifier: Development Status :: 5 - Production/Stable
Classifier: Environment :: Console
Classifier: Intended Audience :: Science/Research
Classifier: Operating System :: OS Independent
Classifier: Programming Language :: Python :: 2.7
Classifier: Programming Language :: Python :: 3.2
Classifier: Programming Language :: Python :: 3.3
Classifier: Programming Language :: Python :: 3.4
Classifier: Programming Language :: Python :: 3.5
Classifier: Topic :: Text Processing :: Linguistic
Classifier: Natural Language :: English
